Metadata-Version: 2.1
Name: odoo14-addon-github_connector_oca
Version: 14.0.1.0.1.dev5
Summary: Add OCA specific information to Odoo modules
Home-page: https://github.com/OCA/interface-github
Author: Odoo Community Association (OCA), Road-Support
Author-email: support@odoo-community.org
License: AGPL-3
Classifier: Programming Language :: Python
Classifier: Framework :: Odoo
Classifier: Framework :: Odoo :: 14.0
Classifier: License :: OSI Approved :: GNU Affero General Public License v3
Requires-Python: >=3.6
Requires-Dist: odoo14-addon-github-connector-odoo
Requires-Dist: odoo<14.1dev,>=14.0a
